story_dialogue_generator/__init__.py
story_dialogue_generator/auth.py
story_dialogue_generator/cli.py
story_dialogue_generator/config.py
story_dialogue_generator/dialogue_service.py
story_dialogue_generator/story_service.py
story_dialogue_generator/version.txt
story_dialogue_generator-1.0.0.dist-info/LICENSE
story_dialogue_generator-1.0.0.dist-info/METADATA
story_dialogue_generator-1.0.0.dist-info/WHEEL
story_dialogue_generator-1.0.0.dist-info/top_level.txt
story_dialogue_generator-1.0.0.dist-info/RECORD
