Metadata-Version: 2.1
Name: story-dialogue-generator
Version: 1.0.0
Summary: Librería para generar diálogos e historias
Author: Narrify
Author-email: Narrify <narrifyengine@gmail.com>
License: Apache License
Project-URL: Source Code, https://github.com/Narrify
Keywords: stories,dialogues,generator,llm,cli
Classifier: Programming Language :: Python :: 3
Classifier: Programming Language :: Python :: 3.7
Classifier: Programming Language :: Python :: 3.8
Classifier: Programming Language :: Python :: 3.9
Classifier: Programming Language :: Python :: 3.10
Classifier: License :: OSI Approved :: MIT License
Classifier: Intended Audience :: Developers
Classifier: Topic :: Software Development :: Libraries
Classifier: Operating System :: OS Independent
Requires-Python: >=3.7
License-File: LICENSE
Requires-Dist: requests >=2.25.1
Requires-Dist: python-dotenv >=0.19.2
Requires-Dist: keyring >=23.0.1
